tensify/__init__.py
Tenseefy-0.0.0.dist-info/LICENSE
Tenseefy-0.0.0.dist-info/METADATA
Tenseefy-0.0.0.dist-info/WHEEL
Tenseefy-0.0.0.dist-info/top_level.txt
Tenseefy-0.0.0.dist-info/RECORD
