Metadata-Version: 2.1
Name: Tenseefy
Version: 0.0.0
Summary: A python package which converts your tenses
Home-page: https://github.com/CodeRustyPro/Tensify
Author: Dev Shah
Author-email: haardmajmudar2827@gmail.com
License: UNKNOWN
Platform: UNKNOWN
Classifier: Programming Language :: Python :: 3
Classifier: License :: OSI Approved :: MIT License
Classifier: Operating System :: OS Independent
